google_auth_st/__init__.py
google_auth_st/aggregate_auth.py
google_auth_st/google_auth.py
google_auth_st-1.3.dist-info/LICENSE
google_auth_st-1.3.dist-info/METADATA
google_auth_st-1.3.dist-info/WHEEL
google_auth_st-1.3.dist-info/top_level.txt
google_auth_st-1.3.dist-info/RECORD
