Metadata-Version: 2.1
Name: google-auth-st
Version: 1.3
Summary: Librería para añadir autenticación con Google en aplicaciones web con el framework de Streamlit.
Home-page: https://github.com/valantoni/google-auth-st.git
Author: Toni Dev
Author-email: classtonidev@gmail.com
License-File: LICENSE
